{
  "uid": "lilnas-storage",
  "title": "Storage",
  "tags": ["lilnas", "storage"],
  "editable": true,
  "graphTooltip": 1,
  "schemaVersion": 39,
  "time": { "from": "now-1h", "to": "now" },
  "refresh": "30s",
  "timezone": "browser",
  "templating": { "list": [] },
  "panels": [
    {
      "id": 1,
      "type": "row",
      "title": "Filesystem Overview",
      "gridPos": { "h": 1, "w": 24, "x": 0, "y": 0 },
      "collapsed": false
    },
    {
      "id": 2,
      "type": "stat",
      "title": "Total Capacity",
      "gridPos": { "h": 4, "w": 4, "x": 0, "y": 1 },
      "datasource": { "type": "prometheus", "uid": "prometheus" },
      "targets": [
        {
          "expr": "sum(node_filesystem_size_bytes{fstype!~\"tmpfs|overlay|squashfs|devtmpfs|fuse.lxcfs\"})",
          "refId": "A"
        }
      ],
      "fieldConfig": {
        "defaults": {
          "unit": "bytes",
          "thresholds": { "steps": [{ "color": "blue", "value": null }] }
        },
        "overrides": []
      },
      "options": {
        "colorMode": "background",
        "graphMode": "none",
        "reduceOptions": { "calcs": ["lastNotNull"] }
      }
    },
    {
      "id": 3,
      "type": "stat",
      "title": "Total Available",
      "gridPos": { "h": 4, "w": 4, "x": 4, "y": 1 },
      "datasource": { "type": "prometheus", "uid": "prometheus" },
      "targets": [
        {
          "expr": "sum(node_filesystem_avail_bytes{fstype!~\"tmpfs|overlay|squashfs|devtmpfs|fuse.lxcfs\"})",
          "refId": "A"
        }
      ],
      "fieldConfig": {
        "defaults": {
          "unit": "bytes",
          "thresholds": {
            "steps": [
              { "color": "red", "value": null },
              { "color": "yellow", "value": 107374182400 },
              { "color": "green", "value": 536870912000 }
            ]
          }
        },
        "overrides": []
      },
      "options": {
        "colorMode": "background",
        "graphMode": "none",
        "reduceOptions": { "calcs": ["lastNotNull"] }
      }
    },
    {
      "id": 4,
      "type": "stat",
      "title": "Total Used",
      "gridPos": { "h": 4, "w": 4, "x": 8, "y": 1 },
      "datasource": { "type": "prometheus", "uid": "prometheus" },
      "targets": [
        {
          "expr": "sum(node_filesystem_size_bytes{fstype!~\"tmpfs|overlay|squashfs|devtmpfs|fuse.lxcfs\"}) - sum(node_filesystem_avail_bytes{fstype!~\"tmpfs|overlay|squashfs|devtmpfs|fuse.lxcfs\"})",
          "refId": "A"
        }
      ],
      "fieldConfig": {
        "defaults": {
          "unit": "bytes",
          "thresholds": { "steps": [{ "color": "orange", "value": null }] }
        },
        "overrides": []
      },
      "options": {
        "colorMode": "background",
        "graphMode": "none",
        "reduceOptions": { "calcs": ["lastNotNull"] }
      }
    },
    {
      "id": 5,
      "type": "gauge",
      "title": "Overall Disk Usage",
      "gridPos": { "h": 4, "w": 4, "x": 12, "y": 1 },
      "datasource": { "type": "prometheus", "uid": "prometheus" },
      "targets": [
        {
          "expr": "(1 - sum(node_filesystem_avail_bytes{fstype!~\"tmpfs|overlay|squashfs|devtmpfs|fuse.lxcfs\"}) / sum(node_filesystem_size_bytes{fstype!~\"tmpfs|overlay|squashfs|devtmpfs|fuse.lxcfs\"})) * 100",
          "refId": "A"
        }
      ],
      "fieldConfig": {
        "defaults": {
          "unit": "percent",
          "min": 0,
          "max": 100,
          "thresholds": {
            "steps": [
              { "color": "green", "value": null },
              { "color": "yellow", "value": 70 },
              { "color": "red", "value": 90 }
            ]
          }
        },
        "overrides": []
      },
      "options": {
        "reduceOptions": { "calcs": ["lastNotNull"] },
        "showThresholdMarkers": true
      }
    },
    {
      "id": 6,
      "type": "stat",
      "title": "Mount Points Monitored",
      "gridPos": { "h": 4, "w": 4, "x": 16, "y": 1 },
      "datasource": { "type": "prometheus", "uid": "prometheus" },
      "targets": [
        {
          "expr": "count(node_filesystem_size_bytes{fstype!~\"tmpfs|overlay|squashfs|devtmpfs|fuse.lxcfs\"})",
          "refId": "A"
        }
      ],
      "fieldConfig": {
        "defaults": {
          "thresholds": { "steps": [{ "color": "blue", "value": null }] }
        },
        "overrides": []
      },
      "options": {
        "colorMode": "background",
        "graphMode": "none",
        "reduceOptions": { "calcs": ["lastNotNull"] }
      }
    },
    {
      "id": 7,
      "type": "stat",
      "title": "Inode Usage",
      "gridPos": { "h": 4, "w": 4, "x": 20, "y": 1 },
      "datasource": { "type": "prometheus", "uid": "prometheus" },
      "targets": [
        {
          "expr": "(1 - sum(node_filesystem_files_free{fstype!~\"tmpfs|overlay|squashfs|devtmpfs|fuse.lxcfs\"}) / sum(node_filesystem_files{fstype!~\"tmpfs|overlay|squashfs|devtmpfs|fuse.lxcfs\"})) * 100",
          "refId": "A"
        }
      ],
      "fieldConfig": {
        "defaults": {
          "unit": "percent",
          "thresholds": {
            "steps": [
              { "color": "green", "value": null },
              { "color": "yellow", "value": 70 },
              { "color": "red", "value": 90 }
            ]
          }
        },
        "overrides": []
      },
      "options": {
        "colorMode": "background",
        "graphMode": "none",
        "reduceOptions": { "calcs": ["lastNotNull"] }
      }
    },
    {
      "id": 10,
      "type": "bargauge",
      "title": "Disk Usage by Mount Point",
      "gridPos": { "h": 10, "w": 24, "x": 0, "y": 5 },
      "datasource": { "type": "prometheus", "uid": "prometheus" },
      "targets": [
        {
          "expr": "(1 - node_filesystem_avail_bytes{fstype!~\"tmpfs|overlay|squashfs|devtmpfs|fuse.lxcfs\"} / node_filesystem_size_bytes{fstype!~\"tmpfs|overlay|squashfs|devtmpfs|fuse.lxcfs\"}) * 100",
          "legendFormat": "{{mountpoint}}",
          "refId": "A"
        }
      ],
      "fieldConfig": {
        "defaults": {
          "unit": "percent",
          "min": 0,
          "max": 100,
          "thresholds": {
            "steps": [
              { "color": "green", "value": null },
              { "color": "yellow", "value": 70 },
              { "color": "orange", "value": 85 },
              { "color": "red", "value": 95 }
            ]
          }
        },
        "overrides": []
      },
      "options": {
        "orientation": "horizontal",
        "displayMode": "gradient",
        "reduceOptions": { "calcs": ["lastNotNull"] },
        "showUnfilled": true,
        "valueMode": "color",
        "namePlacement": "left",
        "text": {}
      }
    },
    {
      "id": 20,
      "type": "row",
      "title": "Filesystem Usage Over Time",
      "gridPos": { "h": 1, "w": 24, "x": 0, "y": 15 },
      "collapsed": false
    },
    {
      "id": 21,
      "type": "timeseries",
      "title": "Disk Usage % by Mount Point",
      "gridPos": { "h": 9, "w": 12, "x": 0, "y": 16 },
      "datasource": { "type": "prometheus", "uid": "prometheus" },
      "targets": [
        {
          "expr": "(1 - node_filesystem_avail_bytes{fstype!~\"tmpfs|overlay|squashfs|devtmpfs|fuse.lxcfs\"} / node_filesystem_size_bytes{fstype!~\"tmpfs|overlay|squashfs|devtmpfs|fuse.lxcfs\"}) * 100",
          "legendFormat": "{{mountpoint}}",
          "refId": "A"
        }
      ],
      "fieldConfig": {
        "defaults": {
          "unit": "percent",
          "min": 0,
          "max": 100,
          "custom": {
            "drawStyle": "line",
            "lineWidth": 2,
            "fillOpacity": 10,
            "showPoints": "never",
            "spanNulls": false
          },
          "thresholds": {
            "steps": [
              { "color": "green", "value": null },
              { "color": "yellow", "value": 70 },
              { "color": "red", "value": 90 }
            ]
          }
        },
        "overrides": []
      },
      "options": {
        "tooltip": { "mode": "multi", "sort": "desc" },
        "legend": {
          "displayMode": "table",
          "placement": "right",
          "calcs": ["lastNotNull", "max"]
        }
      }
    },
    {
      "id": 22,
      "type": "timeseries",
      "title": "Available Space by Mount Point",
      "gridPos": { "h": 9, "w": 12, "x": 12, "y": 16 },
      "datasource": { "type": "prometheus", "uid": "prometheus" },
      "targets": [
        {
          "expr": "node_filesystem_avail_bytes{fstype!~\"tmpfs|overlay|squashfs|devtmpfs|fuse.lxcfs\"}",
          "legendFormat": "{{mountpoint}}",
          "refId": "A"
        }
      ],
      "fieldConfig": {
        "defaults": {
          "unit": "bytes",
          "custom": {
            "drawStyle": "line",
            "lineWidth": 2,
            "fillOpacity": 10,
            "showPoints": "never",
            "spanNulls": false
          }
        },
        "overrides": []
      },
      "options": {
        "tooltip": { "mode": "multi", "sort": "desc" },
        "legend": {
          "displayMode": "table",
          "placement": "right",
          "calcs": ["lastNotNull", "min"]
        }
      }
    },
    {
      "id": 30,
      "type": "row",
      "title": "Disk I/O",
      "gridPos": { "h": 1, "w": 24, "x": 0, "y": 25 },
      "collapsed": false
    },
    {
      "id": 31,
      "type": "stat",
      "title": "Current I/O Operations In Flight",
      "gridPos": { "h": 4, "w": 6, "x": 0, "y": 26 },
      "datasource": { "type": "prometheus", "uid": "prometheus" },
      "targets": [
        {
          "expr": "sum(node_disk_io_now{device=~\"sd.*|nvme.*|vd.*|xvd.*\"})",
          "refId": "A"
        }
      ],
      "fieldConfig": {
        "defaults": {
          "thresholds": {
            "steps": [
              { "color": "green", "value": null },
              { "color": "yellow", "value": 10 },
              { "color": "red", "value": 50 }
            ]
          }
        },
        "overrides": []
      },
      "options": {
        "colorMode": "background",
        "graphMode": "area",
        "reduceOptions": { "calcs": ["lastNotNull"] }
      }
    },
    {
      "id": 32,
      "type": "stat",
      "title": "Total Read Throughput",
      "gridPos": { "h": 4, "w": 6, "x": 6, "y": 26 },
      "datasource": { "type": "prometheus", "uid": "prometheus" },
      "targets": [
        {
          "expr": "sum(irate(node_disk_read_bytes_total{device=~\"sd.*|nvme.*|vd.*|xvd.*\"}[5m]))",
          "refId": "A"
        }
      ],
      "fieldConfig": {
        "defaults": {
          "unit": "Bps",
          "thresholds": { "steps": [{ "color": "blue", "value": null }] }
        },
        "overrides": []
      },
      "options": {
        "colorMode": "background",
        "graphMode": "area",
        "reduceOptions": { "calcs": ["lastNotNull"] }
      }
    },
    {
      "id": 33,
      "type": "stat",
      "title": "Total Write Throughput",
      "gridPos": { "h": 4, "w": 6, "x": 12, "y": 26 },
      "datasource": { "type": "prometheus", "uid": "prometheus" },
      "targets": [
        {
          "expr": "sum(irate(node_disk_written_bytes_total{device=~\"sd.*|nvme.*|vd.*|xvd.*\"}[5m]))",
          "refId": "A"
        }
      ],
      "fieldConfig": {
        "defaults": {
          "unit": "Bps",
          "thresholds": { "steps": [{ "color": "purple", "value": null }] }
        },
        "overrides": []
      },
      "options": {
        "colorMode": "background",
        "graphMode": "area",
        "reduceOptions": { "calcs": ["lastNotNull"] }
      }
    },
    {
      "id": 34,
      "type": "stat",
      "title": "Avg I/O Utilization",
      "gridPos": { "h": 4, "w": 6, "x": 18, "y": 26 },
      "datasource": { "type": "prometheus", "uid": "prometheus" },
      "targets": [
        {
          "expr": "avg(irate(node_disk_io_time_seconds_total{device=~\"sd.*|nvme.*|vd.*|xvd.*\"}[5m])) * 100",
          "refId": "A"
        }
      ],
      "fieldConfig": {
        "defaults": {
          "unit": "percent",
          "thresholds": {
            "steps": [
              { "color": "green", "value": null },
              { "color": "yellow", "value": 50 },
              { "color": "red", "value": 80 }
            ]
          }
        },
        "overrides": []
      },
      "options": {
        "colorMode": "background",
        "graphMode": "area",
        "reduceOptions": { "calcs": ["lastNotNull"] }
      }
    },
    {
      "id": 35,
      "type": "timeseries",
      "title": "Disk Throughput by Device",
      "gridPos": { "h": 9, "w": 12, "x": 0, "y": 30 },
      "datasource": { "type": "prometheus", "uid": "prometheus" },
      "targets": [
        {
          "expr": "irate(node_disk_read_bytes_total{device=~\"sd.*|nvme.*|vd.*|xvd.*\"}[5m])",
          "legendFormat": "{{device}} read",
          "refId": "A"
        },
        {
          "expr": "-irate(node_disk_written_bytes_total{device=~\"sd.*|nvme.*|vd.*|xvd.*\"}[5m])",
          "legendFormat": "{{device}} write",
          "refId": "B"
        }
      ],
      "fieldConfig": {
        "defaults": {
          "unit": "Bps",
          "custom": {
            "drawStyle": "line",
            "lineWidth": 2,
            "fillOpacity": 15,
            "showPoints": "never",
            "spanNulls": false
          }
        },
        "overrides": []
      },
      "options": {
        "tooltip": { "mode": "multi", "sort": "desc" },
        "legend": {
          "displayMode": "table",
          "placement": "bottom",
          "calcs": ["mean", "max"]
        }
      }
    },
    {
      "id": 36,
      "type": "timeseries",
      "title": "IOPS by Device",
      "gridPos": { "h": 9, "w": 12, "x": 12, "y": 30 },
      "datasource": { "type": "prometheus", "uid": "prometheus" },
      "targets": [
        {
          "expr": "irate(node_disk_reads_completed_total{device=~\"sd.*|nvme.*|vd.*|xvd.*\"}[5m])",
          "legendFormat": "{{device}} reads",
          "refId": "A"
        },
        {
          "expr": "-irate(node_disk_writes_completed_total{device=~\"sd.*|nvme.*|vd.*|xvd.*\"}[5m])",
          "legendFormat": "{{device}} writes",
          "refId": "B"
        }
      ],
      "fieldConfig": {
        "defaults": {
          "unit": "iops",
          "custom": {
            "drawStyle": "line",
            "lineWidth": 2,
            "fillOpacity": 15,
            "showPoints": "never",
            "spanNulls": false
          }
        },
        "overrides": []
      },
      "options": {
        "tooltip": { "mode": "multi", "sort": "desc" },
        "legend": {
          "displayMode": "table",
          "placement": "bottom",
          "calcs": ["mean", "max"]
        }
      }
    },
    {
      "id": 37,
      "type": "timeseries",
      "title": "I/O Utilization % by Device",
      "gridPos": { "h": 8, "w": 24, "x": 0, "y": 39 },
      "datasource": { "type": "prometheus", "uid": "prometheus" },
      "targets": [
        {
          "expr": "irate(node_disk_io_time_seconds_total{device=~\"sd.*|nvme.*|vd.*|xvd.*\"}[5m]) * 100",
          "legendFormat": "{{device}}",
          "refId": "A"
        }
      ],
      "fieldConfig": {
        "defaults": {
          "unit": "percent",
          "min": 0,
          "max": 100,
          "custom": {
            "drawStyle": "line",
            "lineWidth": 2,
            "fillOpacity": 20,
            "showPoints": "never",
            "spanNulls": false
          },
          "thresholds": {
            "steps": [
              { "color": "green", "value": null },
              { "color": "yellow", "value": 50 },
              { "color": "red", "value": 80 }
            ]
          }
        },
        "overrides": []
      },
      "options": {
        "tooltip": { "mode": "multi", "sort": "desc" },
        "legend": {
          "displayMode": "table",
          "placement": "right",
          "calcs": ["mean", "max"]
        }
      }
    },
    {
      "id": 40,
      "type": "row",
      "title": "MinIO Object Storage",
      "gridPos": { "h": 1, "w": 24, "x": 0, "y": 47 },
      "collapsed": false
    },
    {
      "id": 41,
      "type": "stat",
      "title": "Cluster Raw Capacity",
      "gridPos": { "h": 4, "w": 4, "x": 0, "y": 48 },
      "datasource": { "type": "prometheus", "uid": "prometheus" },
      "targets": [
        {
          "expr": "minio_cluster_capacity_raw_total_bytes",
          "refId": "A"
        }
      ],
      "fieldConfig": {
        "defaults": {
          "unit": "bytes",
          "thresholds": { "steps": [{ "color": "blue", "value": null }] }
        },
        "overrides": []
      },
      "options": {
        "colorMode": "background",
        "graphMode": "none",
        "reduceOptions": { "calcs": ["lastNotNull"] }
      }
    },
    {
      "id": 42,
      "type": "stat",
      "title": "Usable Capacity",
      "gridPos": { "h": 4, "w": 4, "x": 4, "y": 48 },
      "datasource": { "type": "prometheus", "uid": "prometheus" },
      "targets": [
        {
          "expr": "minio_cluster_capacity_usable_total_bytes",
          "refId": "A"
        }
      ],
      "fieldConfig": {
        "defaults": {
          "unit": "bytes",
          "thresholds": { "steps": [{ "color": "blue", "value": null }] }
        },
        "overrides": []
      },
      "options": {
        "colorMode": "background",
        "graphMode": "none",
        "reduceOptions": { "calcs": ["lastNotNull"] }
      }
    },
    {
      "id": 43,
      "type": "stat",
      "title": "Usable Free Space",
      "gridPos": { "h": 4, "w": 4, "x": 8, "y": 48 },
      "datasource": { "type": "prometheus", "uid": "prometheus" },
      "targets": [
        {
          "expr": "minio_cluster_capacity_usable_free_bytes",
          "refId": "A"
        }
      ],
      "fieldConfig": {
        "defaults": {
          "unit": "bytes",
          "thresholds": {
            "steps": [
              { "color": "red", "value": null },
              { "color": "yellow", "value": 10737418240 },
              { "color": "green", "value": 107374182400 }
            ]
          }
        },
        "overrides": []
      },
      "options": {
        "colorMode": "background",
        "graphMode": "none",
        "reduceOptions": { "calcs": ["lastNotNull"] }
      }
    },
    {
      "id": 44,
      "type": "gauge",
      "title": "Cluster Usage",
      "gridPos": { "h": 4, "w": 4, "x": 12, "y": 48 },
      "datasource": { "type": "prometheus", "uid": "prometheus" },
      "targets": [
        {
          "expr": "(1 - minio_cluster_capacity_usable_free_bytes / minio_cluster_capacity_usable_total_bytes) * 100",
          "refId": "A"
        }
      ],
      "fieldConfig": {
        "defaults": {
          "unit": "percent",
          "min": 0,
          "max": 100,
          "thresholds": {
            "steps": [
              { "color": "green", "value": null },
              { "color": "yellow", "value": 70 },
              { "color": "red", "value": 90 }
            ]
          }
        },
        "overrides": []
      },
      "options": {
        "reduceOptions": { "calcs": ["lastNotNull"] },
        "showThresholdMarkers": true
      }
    },
    {
      "id": 45,
      "type": "stat",
      "title": "Total Objects",
      "gridPos": { "h": 4, "w": 4, "x": 16, "y": 48 },
      "datasource": { "type": "prometheus", "uid": "prometheus" },
      "targets": [
        {
          "expr": "sum(minio_bucket_usage_object_total)",
          "refId": "A"
        }
      ],
      "fieldConfig": {
        "defaults": {
          "thresholds": { "steps": [{ "color": "blue", "value": null }] }
        },
        "overrides": []
      },
      "options": {
        "colorMode": "background",
        "graphMode": "none",
        "reduceOptions": { "calcs": ["lastNotNull"] }
      }
    },
    {
      "id": 46,
      "type": "stat",
      "title": "Total Bucket Usage",
      "gridPos": { "h": 4, "w": 4, "x": 20, "y": 48 },
      "datasource": { "type": "prometheus", "uid": "prometheus" },
      "targets": [
        {
          "expr": "sum(minio_bucket_usage_total_bytes)",
          "refId": "A"
        }
      ],
      "fieldConfig": {
        "defaults": {
          "unit": "bytes",
          "thresholds": { "steps": [{ "color": "orange", "value": null }] }
        },
        "overrides": []
      },
      "options": {
        "colorMode": "background",
        "graphMode": "none",
        "reduceOptions": { "calcs": ["lastNotNull"] }
      }
    },
    {
      "id": 47,
      "type": "bargauge",
      "title": "Usage by Bucket",
      "gridPos": { "h": 8, "w": 12, "x": 0, "y": 52 },
      "datasource": { "type": "prometheus", "uid": "prometheus" },
      "targets": [
        {
          "expr": "minio_bucket_usage_total_bytes",
          "legendFormat": "{{bucket}}",
          "refId": "A"
        }
      ],
      "fieldConfig": {
        "defaults": {
          "unit": "bytes",
          "thresholds": {
            "steps": [
              { "color": "green", "value": null },
              { "color": "yellow", "value": 1073741824 },
              { "color": "red", "value": 10737418240 }
            ]
          }
        },
        "overrides": []
      },
      "options": {
        "orientation": "horizontal",
        "displayMode": "gradient",
        "reduceOptions": { "calcs": ["lastNotNull"] },
        "showUnfilled": true,
        "valueMode": "color",
        "namePlacement": "left",
        "text": {}
      }
    },
    {
      "id": 48,
      "type": "bargauge",
      "title": "Objects by Bucket",
      "gridPos": { "h": 8, "w": 12, "x": 12, "y": 52 },
      "datasource": { "type": "prometheus", "uid": "prometheus" },
      "targets": [
        {
          "expr": "minio_bucket_usage_object_total",
          "legendFormat": "{{bucket}}",
          "refId": "A"
        }
      ],
      "fieldConfig": {
        "defaults": {
          "thresholds": {
            "steps": [{ "color": "blue", "value": null }]
          }
        },
        "overrides": []
      },
      "options": {
        "orientation": "horizontal",
        "displayMode": "gradient",
        "reduceOptions": { "calcs": ["lastNotNull"] },
        "showUnfilled": true,
        "valueMode": "color",
        "namePlacement": "left",
        "text": {}
      }
    },
    {
      "id": 49,
      "type": "timeseries",
      "title": "Bucket Usage Over Time",
      "gridPos": { "h": 9, "w": 12, "x": 0, "y": 60 },
      "datasource": { "type": "prometheus", "uid": "prometheus" },
      "targets": [
        {
          "expr": "minio_bucket_usage_total_bytes",
          "legendFormat": "{{bucket}}",
          "refId": "A"
        }
      ],
      "fieldConfig": {
        "defaults": {
          "unit": "bytes",
          "custom": {
            "drawStyle": "line",
            "lineWidth": 2,
            "fillOpacity": 15,
            "showPoints": "never",
            "spanNulls": false
          }
        },
        "overrides": []
      },
      "options": {
        "tooltip": { "mode": "multi", "sort": "desc" },
        "legend": {
          "displayMode": "table",
          "placement": "bottom",
          "calcs": ["lastNotNull", "max"]
        }
      }
    },
    {
      "id": 50,
      "type": "timeseries",
      "title": "MinIO Cluster Free Space Over Time",
      "gridPos": { "h": 9, "w": 12, "x": 12, "y": 60 },
      "datasource": { "type": "prometheus", "uid": "prometheus" },
      "targets": [
        {
          "expr": "minio_cluster_capacity_usable_free_bytes",
          "legendFormat": "Usable Free",
          "refId": "A"
        },
        {
          "expr": "minio_cluster_capacity_usable_total_bytes",
          "legendFormat": "Usable Total",
          "refId": "B"
        }
      ],
      "fieldConfig": {
        "defaults": {
          "unit": "bytes",
          "custom": {
            "drawStyle": "line",
            "lineWidth": 2,
            "fillOpacity": 10,
            "showPoints": "never",
            "spanNulls": false
          }
        },
        "overrides": []
      },
      "options": {
        "tooltip": { "mode": "multi", "sort": "desc" },
        "legend": {
          "displayMode": "table",
          "placement": "bottom",
          "calcs": ["lastNotNull", "min"]
        }
      }
    }
  ]
}
